setup.cfg
setup.py
rapidpg/__init__.py
rapidpg/__main__.py
rapidpg/level_converter.py
rapidpg/utilities.py
rapidpg.egg-info/PKG-INFO
rapidpg.egg-info/SOURCES.txt
rapidpg.egg-info/dependency_links.txt
rapidpg.egg-info/top_level.txt
rapidpg/levelmgr/__init__.py
rapidpg/levelmgr/camera.py
rapidpg/levelmgr/collision.py
rapidpg/loader/__init__.py
rapidpg/loader/image.py
rapidpg/types/__init__.py
rapidpg/types/animation.py
rapidpg/types/player.py