Metadata-Version: 1.1
Name: rapidpg
Version: 0.3.1
Summary: A collections of tools for rapid game developement with pygame
Home-page: https://github.com/XrXr/RapidPygame
Author: XrXr
Author-email: xrsquared@gmail.com
License: UNKNOWN
Download-URL: https://github.com/XrXr/RapidPygame/tarball/0.3.1
Keywords: game developement,pygame
Platform: UNKNOWN
